LICENSE
MANIFEST.in
README.rst
VERSION
requirements.txt
setup.py
unicore/__init__.py
unicore/__init__.pyc
unicore.google.egg-info/PKG-INFO
unicore.google.egg-info/SOURCES.txt
unicore.google.egg-info/dependency_links.txt
unicore.google.egg-info/namespace_packages.txt
unicore.google.egg-info/not-zip-safe
unicore.google.egg-info/requires.txt
unicore.google.egg-info/top_level.txt
unicore/google/__init__.py
unicore/google/__init__.pyc
unicore/google/tasks.py
unicore/google/tasks.pyc
unicore/google/tests/test_tasks.py
unicore/google/tests/__pycache__/test_tasks.cpython-27-PYTEST.pyc