Metadata-Version: 1.1
Name: unicore.google
Version: 0.0.1
Summary: Tools for dealing with Google from Universal Core
Home-page: http://github.com/universalcore/unicore.google
Author: Praekelt Foundation
Author-email: dev@praekelt.com
License: BSD
Keywords: google,universal,core
Platform: UNKNOWN
Classifier: Programming Language :: Python
Classifier: Framework :: Pyramid
Classifier: Topic :: Internet :: WWW/HTTP
Classifier: Topic :: Internet :: WWW/HTTP :: WSGI :: Application
